jsonobject/utils.c
jsonobject/containers.cpython-313-x86_64-linux-gnu.so
jsonobject/api.c
jsonobject/__init__.py
jsonobject/containers.c
jsonobject/base_properties.c
jsonobject/properties.pyx
jsonobject/properties.cpython-313-x86_64-linux-gnu.so
jsonobject/base.pyx
jsonobject/utils.pyx
jsonobject/base_properties.cpython-313-x86_64-linux-gnu.so
jsonobject/utils.cpython-313-x86_64-linux-gnu.so
jsonobject/api.pyx
jsonobject/base.c
jsonobject/api.cpython-313-x86_64-linux-gnu.so
jsonobject/exceptions.py
jsonobject/containers.pyx
jsonobject/base_properties.pyx
jsonobject/base.cpython-313-x86_64-linux-gnu.so
jsonobject/properties.c
jsonobject-2.3.0.dist-info/LICENSE
jsonobject-2.3.0.dist-info/WHEEL
jsonobject-2.3.0.dist-info/METADATA
jsonobject-2.3.0.dist-info/top_level.txt
jsonobject-2.3.0.dist-info/RECORD
