Metadata-Version: 2.2
Name: jsonobject
Version: 2.3.0
Summary: A library for dealing with JSON as python objects
Author-email: Danny Roberts <droberts@dimagi.com>
License: Copyright (c) 2013-2014, Dimagi Inc., and individual contributors.
Project-URL: Home, https://github.com/dimagi/jsonobject
Classifier: Programming Language :: Python
Classifier: Programming Language :: Python :: 3
Classifier: Programming Language :: Python :: 3.9
Classifier: Programming Language :: Python :: 3.10
Classifier: Programming Language :: Python :: 3.11
Classifier: Programming Language :: Python :: 3.12
Classifier: Programming Language :: Python :: 3.13
Classifier: License :: OSI Approved :: BSD License
Requires-Python: >=3.9
License-File: LICENSE
